noob3a/__init__.py
noob3a/noob3a.py
pynoob3a-0.0.1.dist-info/LICENSE.md
pynoob3a-0.0.1.dist-info/METADATA
pynoob3a-0.0.1.dist-info/WHEEL
pynoob3a-0.0.1.dist-info/top_level.txt
pynoob3a-0.0.1.dist-info/RECORD
