Metadata-Version: 2.1
Name: pynoob3a
Version: 0.0.1
Summary: dumb binary format
Home-page: UNKNOWN
Author: noobermin
Author-email: ngirmang@protonmail.com
License: MIT
Platform: UNKNOWN
